{"ff1JktJ9vSsfG/G/UtW78w==":"img-2919-2000x2000.jpg","so9XYI9I6AsBn2XZWT2pmw==":"personal%20branding-122x78.png","hV7I/C3xTGt8viSnFIIckA==":"personal%20branding-190x122.png","F0VWTqGcENVHOoT6pMVcZQ==":"personal%20branding-190x122.png","qt5C/2xev3swQswZ7bTiNQ==":"mbr-795x1080.jpg","SNAY9JCkBhjwGmdt/3Ipsw==":"mbr-864x1080.jpg","7ZG3EVOJczAqTiImzMNuMQ==":"145-400x500.jpg","2YItOywK8Nof/rWWrDLSqQ==":"graduation-cap-64x64.png","hr1TRTX8o8S+qIe6dG9FVQ==":"graduation-cap-1-64x64.png","b8ChsPZQw5jhH2RDz/EYXw==":"graduation-cap-2-64x64.png","NBeRvGcH5uJp6ycGjhXatA==":"background4.jpg","4+DzqXFpj/z2AIwVP9lcYQ==":"background5.jpg","+tpTjSGNEiAYzt9rsNH85Q==":"laptop-880x598.png","Ly+mdm63lVz6CqSX2vcU6g==":"background3.jpg","dtsftbSzH9lf+m+ISjdf4g==":"0-240x240.jpg","yDYxx/Idf5fLZ24gGr8Itg==":"img_9227-3-1729x1297.jpg","0Z1WjPof1H2ex2M9aNGznQ==":"png%20ste-3339x3326.png","uh7Q3KcKUS2rFUuI4lR0mw==":"laptop2-2-1440x692.png","jYUJfpMvoigCLO7flB03Dw==":"fb%20ig-1014x478.png","cH+j5kVsIc87wzKzOSTv+A==":"mbr-1-810x1080.jpg","ihlkf69UyfSmhSyJ1Jvc6w==":"jumbotron.jpg","eEeCmXN/xcvUL7PJ/Grz+g==":"fireshot%20capture%2022%20-%20mikos%20barbers%20on%20instagram_%20%E2%80%9Cbook%20_%20-%20https___www.instagram.com_p_bhnrusrfjbm_-542x596.png","roGocHfvHa39Ow5VadCKKg==":"21192647_1472467449511550_9008668666634761011_n-300x300.png","CMmhj+jjtqY9vB+gOUFTXg==":"12313992_1681631398717151_2316207709280031027_n-240x240.jpg","GIt4fftnrDcbJTHnPPrPGA==":"mbr-1-1620x1080.jpg","lHmtoWQX9IlTGvAD8Tf8fA==":"mbr-1014x674.jpg"}